pitchoune/__init__.py
pitchoune/chat.py
pitchoune/decorators.py
pitchoune/factory.py
pitchoune/io.py
pitchoune/super_factory.py
pitchoune/utils.py
pitchoune/chats/__init__.py
pitchoune/chats/ollama_chat.py
pitchoune/chats/openai_chat.py
pitchoune/factories/__init__.py
pitchoune/factories/chat_factory.py
pitchoune/factories/io_factory.py
pitchoune/ios/__init__.py
pitchoune/ios/csv_io.py
pitchoune/ios/jsonl_io.py
pitchoune/ios/xlsm_io.py
pitchoune/ios/xlsx_io.py
pitchoune-0.60.4.dist-info/licenses/LICENSE
pitchoune-0.60.4.dist-info/METADATA
pitchoune-0.60.4.dist-info/WHEEL
pitchoune-0.60.4.dist-info/top_level.txt
pitchoune-0.60.4.dist-info/RECORD
