Metadata-Version: 2.4
Name: pitchoune
Version: 0.60.4
Summary: Load & save data & chat with LLMs
Home-page: https://github.com/pe-brian/pitchoune
Author: Pierre-Emmanuel Brian
Author-email: pebrian@outlook.fr
Project-URL: Bug Tracker, https://github.com/pe-brian/pitchoune/issues
Classifier: Programming Language :: Python :: 3
Classifier: License :: OSI Approved :: MIT License
Classifier: Operating System :: OS Independent
Requires-Python: >=3.12.2
License-File: LICENSE
Requires-Dist: polars>=1.29.0
Dynamic: license-file
